multigrad/__init__.py
multigrad/_version.py
multigrad/adam.py
multigrad/bfgs.py
multigrad/multigrad.py
multigrad/util.py
multigrad/diffdesi_experimental/util.py
multigrad/mpi4jax/__init__.py
multigrad/mpi4jax/multigrad.py
multigrad-1.0.0.dist-info/LICENSE
multigrad-1.0.0.dist-info/METADATA
multigrad-1.0.0.dist-info/WHEEL
multigrad-1.0.0.dist-info/top_level.txt
multigrad-1.0.0.dist-info/RECORD
