Metadata-Version: 2.1
Name: multigrad
Version: 1.0.0
Summary: Differentiable Multiprocessing for Gradient Descent with JAX
Author-email: Alan Pearl <alanpearl13@gmail.com>
License: MIT License
Project-URL: home, https://github.com/AlanPearl/multigrad
Classifier: Programming Language :: Python :: 3
Requires-Python: >=3.8
License-File: LICENSE
Requires-Dist: numpy
Requires-Dist: jax
Requires-Dist: scipy
